lmake/__init__.py
lmake/cpplint.py
lmake/blade3/Makefile.header
lmake/blade3/__init__.py
lmake/blade3/__main__.py
lmake/blade3/cc.py
lmake/blade3/color_print.py
lmake/blade3/config.py
lmake/blade3/data.py
lmake/blade3/gen_makefile.sh
lmake/blade3/genrule.py
lmake/blade3/java.py
lmake/blade3/nolint.txt
lmake/blade3/package.py
lmake/blade3/pconfig.py
lmake/blade3/regen_makefile.py
lmake/blade3/repo_check.py
lmake/blade3/rule.py
lmake/blade3/rule_generator.py
lmake/blade3/shell.py
lmake/blade3/.blade/all_deps
lmake/blade3/.blade/exe_files
lmake/blade3/.blade/files_to_pub
lmake/blade3/.blade/src_files
lmake/build_tools/third_party/include/README.md
lmake/build_tools/third_party/lib/m32/libtcmalloc_minimal.a
lmake/build_tools/third_party/lib/m64/libtcmalloc_minimal.a
lmake/build_tools/third_party/m32/include/curl/curl.h
lmake/build_tools/third_party/m32/include/curl/curlver.h
lmake/build_tools/third_party/m32/include/curl/easy.h
lmake/build_tools/third_party/m32/include/curl/mprintf.h
lmake/build_tools/third_party/m32/include/curl/multi.h
lmake/build_tools/third_party/m32/include/curl/stdcheaders.h
lmake/build_tools/third_party/m32/include/curl/system.h
lmake/build_tools/third_party/m32/include/curl/typecheck-gcc.h
lmake/build_tools/third_party/m32/include/gflags/defines.h
lmake/build_tools/third_party/m32/include/gflags/gflags.h
lmake/build_tools/third_party/m32/include/gflags/gflags_completions.h
lmake/build_tools/third_party/m32/include/gflags/gflags_declare.h
lmake/build_tools/third_party/m32/include/gflags/gflags_gflags.h
lmake/build_tools/third_party/m32/include/glog/log_severity.h
lmake/build_tools/third_party/m32/include/glog/logging.h
lmake/build_tools/third_party/m32/include/glog/raw_logging.h
lmake/build_tools/third_party/m32/include/glog/stl_logging.h
lmake/build_tools/third_party/m32/include/glog/vlog_is_on.h
lmake/build_tools/third_party/m32/lib/libcurl.a
lmake/build_tools/third_party/m32/lib/libcurl.la
lmake-1.0.11.dist-info/METADATA
lmake-1.0.11.dist-info/RECORD
lmake-1.0.11.dist-info/WHEEL
lmake-1.0.11.dist-info/entry_points.txt
lmake-1.0.11.dist-info/top_level.txt
