Metadata-Version: 2.1
Name: lmake
Version: 1.0.11
Summary: Another makefile generator
Home-page: https://github.com/AgoraLab/media_build
Author: Cloud platform @ Agora.io
Author-email: wanghaotian@agora.io
License: UNKNOWN
Platform: UNKNOWN
Classifier: Programming Language :: Python :: 2.7
